composo/__init__.py
composo/py.typed
composo/adapters/__init__.py
composo/adapters/anthropic_adapter.py
composo/adapters/base.py
composo/adapters/factory.py
composo/adapters/openai_adapter.py
composo/client/__init__.py
composo/client/async_client.py
composo/client/base.py
composo/client/sync.py
composo/client/types.py
composo/exceptions/__init__.py
composo/exceptions/api_exceptions.py
composo/models/__init__.py
composo/models/api_types.py
composo/models/client_models.py
composo/models/common_types.py
composo/models/criteria.py
composo/models/openinference.py
composo/models/requests.py
composo/models/responses.py
composo/tracing/__init__.py
composo/tracing/agent_tracer.py
composo/tracing/setup.py
composo/tracing/parsers/__init__.py
composo/tracing/parsers/anthropic.py
composo/tracing/parsers/base.py
composo/tracing/parsers/common.py
composo/tracing/parsers/google_genai.py
composo/tracing/parsers/openai.py
composo/utils/__init__.py
composo/utils/validation.py
composo-0.2.48.dist-info/METADATA
composo-0.2.48.dist-info/WHEEL
composo-0.2.48.dist-info/top_level.txt
composo-0.2.48.dist-info/RECORD
