Metadata-Version: 2.4
Name: composo
Version: 0.2.48
Summary: Composo Python SDK
Author-email: Haoguo WU <haoguo@composo.ai>, Luke Markham <luke@composo.ai>
Classifier: Development Status :: 3 - Alpha
Classifier: Intended Audience :: Developers
Classifier: License :: OSI Approved :: MIT License
Classifier: Programming Language :: Python :: 3
Classifier: Programming Language :: Python :: 3.8
Classifier: Programming Language :: Python :: 3.9
Classifier: Programming Language :: Python :: 3.10
Classifier: Programming Language :: Python :: 3.11
Requires-Python: >=3.8
Requires-Dist: httpx>=0.21.0
Requires-Dist: pydantic<3.0.0,>=1.9.2
Requires-Dist: typing-extensions>=4.0.0
Requires-Dist: deepdiff>=6.0.0
Requires-Dist: openai>=1.0.0
Requires-Dist: anthropic>=0.25.0
Requires-Dist: tenacity>=8.0.0
Requires-Dist: json2xml>=3.5.0
Requires-Dist: opentelemetry-api>=1.20.0
Requires-Dist: opentelemetry-sdk>=1.20.0
Requires-Dist: openinference-instrumentation-openai>=0.1.34
Requires-Dist: openinference-instrumentation-anthropic>=0.1.0
Provides-Extra: test
Requires-Dist: pytest>=7.0.0; extra == "test"
Requires-Dist: pytest-asyncio>=0.21.0; extra == "test"
Requires-Dist: pytest-cov>=4.0.0; extra == "test"
Requires-Dist: langchain>=1.0.0; extra == "test"
Requires-Dist: langgraph>=1.0.0; extra == "test"
Requires-Dist: langchain-openai>=1.0.0; extra == "test"
Requires-Dist: langchain-anthropic>=1.0.0; extra == "test"
Provides-Extra: dev
Requires-Dist: pytest>=7.0.0; extra == "dev"
Requires-Dist: pytest-asyncio>=0.21.0; extra == "dev"
Requires-Dist: pytest-cov>=4.0.0; extra == "dev"
Requires-Dist: black>=23.0.0; extra == "dev"
Requires-Dist: isort>=5.12.0; extra == "dev"
Requires-Dist: mypy>=1.0.0; extra == "dev"
Requires-Dist: flake8>=6.0.0; extra == "dev"
Requires-Dist: build>=0.10.0; extra == "dev"
Requires-Dist: twine>=4.0.0; extra == "dev"
